{
  "$schema": "https://biomejs.dev/schemas/1.7.3/schema.json",
  "organizeImports": {
    "enabled": true
  },
  "files": {
    "ignore": [
      "**/package.json",
      "**/dist/**",
      "**/build/**",
      "node_modules/**",
      "**/*.js"
    ]
  },
  "formatter": {
    "enabled": true,
    "formatWithErrors": false,
    "ignore": [],
    "attributePosition": "auto",
    "indentStyle": "space",
    "indentWidth": 2,
    "lineEnding": "lf",
    "lineWidth": 80
  },

  "javascript": {
    "formatter": {
      "arrowParentheses": "always",
      "bracketSameLine": false,
      "bracketSpacing": true,
      "jsxQuoteStyle": "double",
      "quoteProperties": "asNeeded",
      "semicolons": "always"
    }
  },
  "json": {
    "formatter": {
      "trailingCommas": "none"
    }
  },
  "linter": {
    "enabled": true,
    "rules": {
      "a11y": {
        "useKeyWithClickEvents": "off"
      },
      "suspicious": {
        "noExplicitAny": "off",
        "noArrayIndexKey": "off"
      },
      "correctness": {
        "noUnusedImports": "error",
        "useExhaustiveDependencies": "off"
      },
      "complexity": {
        "useLiteralKeys": "off"
      },
      "style": {
        "useNodejsImportProtocol": "off",
        "noNonNullAssertion": "off",
        "noParameterAssign": "off"
      },
      "recommended": true
    }
  }
}
